[
  {
    "ContainingType": "DockerWebAPI.Controllers.BrandController",
    "Method": "GetAllBrands",
    "RelativePath": "api/Brand",
    "HttpMethod": "GET",
    "IsController": true,
    "Order": 0,
    "Parameters": [],
    "ReturnTypes": []
  },
  {
    "ContainingType": "NormalWebAPI.Controllers.WeatherForecastController",
    "Method": "Get",
    "RelativePath": "WeatherForecast",
    "HttpMethod": "GET",
    "IsController": true,
    "Order": 0,
    "Parameters": [],
    "ReturnTypes": [
      {
        "Type": "System.Collections.Generic.IEnumerable\u00601[[NormalWebAPI.WeatherForecast, NormalWebAPI, Version=1.0.0.0, Culture=neutral, PublicKeyToken=null]]",
        "MediaTypes": [
          "text/plain",
          "application/json",
          "text/json"
        ],
        "StatusCode": 200
      }
    ]
  }
]